thefuck_ai_assistant/__init__.py
thefuck_ai_assistant/copy_source.py
thefuck_ai_assistant/installer.py
thefuck_ai_assistant/rule.py
thefuck_ai_assistant/shell_compat_test.py
thefuck_ai_assistant/test.py
thefuck_ai_rule-0.1.7.dist-info/licenses/LICENSE
thefuck_ai_rule-0.1.7.dist-info/METADATA
thefuck_ai_rule-0.1.7.dist-info/WHEEL
thefuck_ai_rule-0.1.7.dist-info/entry_points.txt
thefuck_ai_rule-0.1.7.dist-info/top_level.txt
thefuck_ai_rule-0.1.7.dist-info/RECORD
