Metadata-Version: 2.4
Name: thefuck-ai-rule
Version: 0.1.7
Summary: AI-powered command correction assistant for thefuck
Home-page: https://github.com/huchiyv/thefuckAiRule
Author: huchiyv
Author-email: huchiyv <14727672368@163.com>
Classifier: Programming Language :: Python :: 3
Classifier: License :: OSI Approved :: MIT License
Classifier: Operating System :: OS Independent
Requires-Python: >=3.6
License-File: LICENSE
Requires-Dist: requests>=2.25.0
Requires-Dist: thefuck>=3.0
Dynamic: author
Dynamic: home-page
Dynamic: license-file
Dynamic: requires-python
